pydantic_property/__init__.py
pydantic_property/__meta__.py
pydantic_property/prop.py
pydantic_property/__pycache__/__init__.cpython-38.pyc
pydantic_property/__pycache__/__meta__.cpython-38.pyc
pydantic_property/__pycache__/prop.cpython-38.pyc
pydantic_property-0.0.1.dist-info/LICENSE
pydantic_property-0.0.1.dist-info/METADATA
pydantic_property-0.0.1.dist-info/WHEEL
pydantic_property-0.0.1.dist-info/top_level.txt
pydantic_property-0.0.1.dist-info/RECORD
