Metadata-Version: 2.1
Name: pydantic-property
Version: 0.0.1
Summary: Property descriptors for Pydantic
Home-page: https://github.com/justengel/pydantic_property
Author: Justin Engel
Author-email: jtengel08@gmail.com
License: MIT
Download-URL: https://github.com/justengel/pydantic_property/archive/v0.0.1.tar.gz
Keywords: pydantic property descriptor
Platform: any
Classifier: Programming Language :: Python
Classifier: Programming Language :: Python :: 3
Classifier: Operating System :: OS Independent
Requires-Dist: pydantic (>=1.5.1)
